ShiyanlouSuanfaJiaochengHeji20160904/README.md
ShiyanlouSuanfaJiaochengHeji20160904/__init__.py
ShiyanlouSuanfaJiaochengHeji20160904/__main__.py
ShiyanlouSuanfaJiaochengHeji20160904/file.epub
ShiyanlouSuanfaJiaochengHeji20160904/index.html
ShiyanlouSuanfaJiaochengHeji20160904/css/__init__.py
ShiyanlouSuanfaJiaochengHeji20160904/css/annotations.css
ShiyanlouSuanfaJiaochengHeji20160904/css/main.css
ShiyanlouSuanfaJiaochengHeji20160904/css/normalize.css
ShiyanlouSuanfaJiaochengHeji20160904/css/popup.css
ShiyanlouSuanfaJiaochengHeji20160904/font/__init__.py
ShiyanlouSuanfaJiaochengHeji20160904/font/fontello.eot
ShiyanlouSuanfaJiaochengHeji20160904/font/fontello.svg
ShiyanlouSuanfaJiaochengHeji20160904/font/fontello.ttf
ShiyanlouSuanfaJiaochengHeji20160904/font/fontello.woff
ShiyanlouSuanfaJiaochengHeji20160904/img/__init__.py
ShiyanlouSuanfaJiaochengHeji20160904/img/annotator-glyph-sprite.png
ShiyanlouSuanfaJiaochengHeji20160904/img/annotator-icon-sprite.png
ShiyanlouSuanfaJiaochengHeji20160904/img/apple-touch-icon.png
ShiyanlouSuanfaJiaochengHeji20160904/img/cancelfullscreen.png
ShiyanlouSuanfaJiaochengHeji20160904/img/close.png
ShiyanlouSuanfaJiaochengHeji20160904/img/fullscreen.png
ShiyanlouSuanfaJiaochengHeji20160904/img/loader.gif
ShiyanlouSuanfaJiaochengHeji20160904/img/menu-icon.png
ShiyanlouSuanfaJiaochengHeji20160904/img/save.png
ShiyanlouSuanfaJiaochengHeji20160904/img/saved.png
ShiyanlouSuanfaJiaochengHeji20160904/img/settings-s.png
ShiyanlouSuanfaJiaochengHeji20160904/img/settings.png
ShiyanlouSuanfaJiaochengHeji20160904/img/star.png
ShiyanlouSuanfaJiaochengHeji20160904/js/__init__.py
ShiyanlouSuanfaJiaochengHeji20160904/js/epub.js
ShiyanlouSuanfaJiaochengHeji20160904/js/epub.min.js
ShiyanlouSuanfaJiaochengHeji20160904/js/epub.min.map
ShiyanlouSuanfaJiaochengHeji20160904/js/hooks.min.js
ShiyanlouSuanfaJiaochengHeji20160904/js/hooks.min.map
ShiyanlouSuanfaJiaochengHeji20160904/js/reader.js
ShiyanlouSuanfaJiaochengHeji20160904/js/reader.js.map
shiyanlou_suanfa_jiaocheng_heji_20160904-2024.3.2.0.dist-info/METADATA
shiyanlou_suanfa_jiaocheng_heji_20160904-2024.3.2.0.dist-info/WHEEL
shiyanlou_suanfa_jiaocheng_heji_20160904-2024.3.2.0.dist-info/entry_points.txt
shiyanlou_suanfa_jiaocheng_heji_20160904-2024.3.2.0.dist-info/top_level.txt
shiyanlou_suanfa_jiaocheng_heji_20160904-2024.3.2.0.dist-info/RECORD
